README.rst
setup.cfg
setup.py
tests.py
tox.ini
version.py
setuptools_git_version.egg-info/PKG-INFO
setuptools_git_version.egg-info/SOURCES.txt
setuptools_git_version.egg-info/dependency_links.txt
setuptools_git_version.egg-info/entry_points.txt
setuptools_git_version.egg-info/requires.txt
setuptools_git_version.egg-info/top_level.txt