Metadata-Version: 1.1
Name: setuptools-git-version
Version: 1.0.2
Summary: Automatically set package version from Git.
Home-page: https://github.com/pyfidelity/setuptools-git-version
Author: pyfidelity UG
Author-email: mail@pyfidelity.com
License: http://opensource.org/licenses/MIT
Platform: UNKNOWN
Classifier: Framework :: Setuptools Plugin
Classifier: Intended Audience :: Developers
Classifier: License :: OSI Approved :: MIT License
Classifier: Programming Language :: Python
